aikframe/RPC.py
aikframe/__init__.py
aikframe/decoder.py
aikframe/listener.py
aikframe/msgpacket.py
aikframe/streaming.py
aikframe-0.1.0.dist-info/METADATA
aikframe-0.1.0.dist-info/WHEEL
aikframe-0.1.0.dist-info/top_level.txt
aikframe-0.1.0.dist-info/RECORD
