Metadata-Version: 2.1
Name: aikframe
Version: 0.1.0
Summary: Aikframe: 模块化云湖机器人开发框架
Home-page: https://github.com/lilingyi-awa/aikframe
Author: Project VsingerXiaoice Consensus
Author-email: alan_sudo@yeah.net
License: Public Domain Mark
Requires: aiohttp
Requires: pydantic
